{
  "api": "search",
  "file": "/test/free/search/350_point_in_time.yml",
  "name": "point-in-time with index filter",
  "origin": "yaml",
  "request": {
    "args": {
      "body": {
        "pit": {
          "id": "yKiyBAEFdGVzdDIWdnFySUpXektTRUd0R2hwSUlzd09BZwABFlJQS1JUeThuVEdteU1wNW43MjZJYWcAAQAAAAAAAAazFmhYcHNqX3ZKUWRXNGI3anpiT0wwV2cAAhZ2cXJJSld6S1NFR3RHaHBJSXN3T0FnAAAWNWY4Q2VOMWVUVm0wbnJ3dS1BWnVLdwAA"
        },
        "size": 1
      },
      "typed_keys": true
    }
  },
  "response": {
    "headers": {
      "content-type": "application/json",
      "transfer-encoding": "chunked",
      "x-elastic-product": "Elasticsearch"
    },
    "payload": {
      "_shards": {
        "failed": 0,
        "skipped": 0,
        "successful": 1,
        "total": 1
      },
      "hits": {
        "hits": [
          {
            "_id": "45",
            "_index": "test2",
            "_score": 1,
            "_source": {
              "age": 19,
              "birth": "2023-01-01",
              "foo": "bar",
              "id": 45
            }
          }
        ],
        "max_score": 1,
        "total": {
          "relation": "eq",
          "value": 1
        }
      },
      "pit_id": "yKiyBAEFdGVzdDIWdnFySUpXektTRUd0R2hwSUlzd09BZwABFlJQS1JUeThuVEdteU1wNW43MjZJYWcAAQAAAAAAAAazFmhYcHNqX3ZKUWRXNGI3anpiT0wwV2cAAhZ2cXJJSld6S1NFR3RHaHBJSXN3T0FnAAAWNWY4Q2VOMWVUVm0wbnJ3dS1BWnVLdwAA",
      "timed_out": false,
      "took": 0
    },
    "statusCode": 200
  }
}