{
  "api": "security.create_api_key",
  "file": "/test/platinum/api_key/10_basic.yml",
  "name": "Test invalidate api keys",
  "origin": "yaml",
  "request": {
    "args": {
      "body": {
        "expiration": "1d",
        "name": "my-api-key-1",
        "role_descriptors": {
        }
      }
    },
    "headers": {
      "Authorization": "Basic YXBpX2tleV91c2VyOngtcGFjay10ZXN0LXBhc3N3b3Jk"
    }
  },
  "response": {
    "headers": {
      "content-length": "186",
      "content-type": "application/json",
      "x-elastic-product": "Elasticsearch"
    },
    "payload": {
      "api_key": "LYNFox7j0s16ij9D4aSgHA",
      "encoded": "Tmo2eWpac0JENEFDMFNJNVl6dUU6TFlORm94N2owczE2aWo5RDRhU2dIQQ==",
      "expiration": 1767695236999,
      "id": "Nj6yjZsBD4AC0SI5YzuE",
      "name": "my-api-key-1"
    },
    "statusCode": 200
  }
}