{
  "api": "security.get_api_key",
  "file": "/test/platinum/api_key/60_admin_user.yml",
  "name": "Test update api keys",
  "origin": "yaml",
  "request": {
    "args": {
      "id": "DJ7r4pYBQX361djww7gd"
    }
  },
  "response": {
    "headers": {
      "content-length": "389",
      "content-type": "application/json",
      "x-elastic-product": "Elasticsearch"
    },
    "payload": {
      "api_keys": [
        {
          "creation": 1747563823902,
          "expiration": 1747650223902,
          "id": "DJ7r4pYBQX361djww7gd",
          "invalidated": false,
          "metadata": {
            "step": 1
          },
          "name": "api-key-update",
          "realm": "reserved",
          "realm_type": "reserved",
          "role_descriptors": {
            "access": {
              "applications": [
              ],
              "cluster": [
                "monitor"
              ],
              "indices": [
              ],
              "metadata": {
              },
              "run_as": [
              ],
              "transient_metadata": {
                "enabled": true
              }
            }
          },
          "type": "rest",
          "username": "elastic"
        }
      ]
    },
    "statusCode": 200
  }
}