{
  "api": "security.query_api_keys",
  "file": "/test/platinum/api_key/60_admin_user.yml",
  "name": "Test query api keys",
  "origin": "yaml",
  "request": {
    "args": {
      "body": {
      },
      "typed_keys": true
    }
  },
  "response": {
    "headers": {
      "content-length": "3952",
      "content-type": "application/json",
      "x-elastic-product": "Elasticsearch"
    },
    "payload": {
      "api_keys": [
        {
          "creation": 1765535304585,
          "id": "F3gaEpsBbCMe6CnBy_KI",
          "invalidated": false,
          "metadata": {
          },
          "name": "api-key-1",
          "realm": "default_native",
          "realm_type": "native",
          "role_descriptors": {
          },
          "type": "rest",
          "username": "api_key_user_1"
        },
        {
          "creation": 1765535305238,
          "id": "GXgaEpsBbCMe6CnBzvIV",
          "invalidated": false,
          "metadata": {
          },
          "name": "api-key-2",
          "realm": "default_native",
          "realm_type": "native",
          "role_descriptors": {
          },
          "type": "rest",
          "username": "api_key_user_1"
        },
        {
          "creation": 1765535269290,
          "expiration": 1765621669290,
          "id": "33gaEpsBbCMe6CnBQfGm",
          "invalidated": true,
          "invalidation": 1765535271969,
          "metadata": {
          },
          "name": "my-api-key-1",
          "realm": "default_native",
          "realm_type": "native",
          "role_descriptors": {
          },
          "type": "rest",
          "username": "api_key_user"
        },
        {
          "creation": 1765535269940,
          "expiration": 1765621669940,
          "id": "4XgaEpsBbCMe6CnBRPEy",
          "invalidated": true,
          "invalidation": 1765535271969,
          "metadata": {
          },
          "name": "my-api-key-2",
          "realm": "default_native",
          "realm_type": "native",
          "role_descriptors": {
          },
          "type": "rest",
          "username": "api_key_user"
        },
        {
          "creation": 1765535270951,
          "expiration": 1765621670951,
          "id": "43gaEpsBbCMe6CnBSPEm",
          "invalidated": true,
          "invalidation": 1765535271969,
          "metadata": {
          },
          "name": "my-api-key-3",
          "realm": "default_native",
          "realm_type": "native",
          "role_descriptors": {
          },
          "type": "rest",
          "username": "api_key_user"
        },
        {
          "creation": 1765535275063,
          "expiration": 1765621675063,
          "id": "6XgaEpsBbCMe6CnBWPE1",
          "invalidated": true,
          "invalidation": 1765535275991,
          "metadata": {
          },
          "name": "user1-api-key",
          "realm": "default_native",
          "realm_type": "native",
          "role_descriptors": {
          },
          "type": "rest",
          "username": "api_key_user_1"
        },
        {
          "creation": 1765535274504,
          "expiration": 1765621674504,
          "id": "53gaEpsBbCMe6CnBVvEF",
          "invalidated": true,
          "invalidation": 1765535277004,
          "metadata": {
          },
          "name": "manager-api-key",
          "realm": "default_native",
          "realm_type": "native",
          "role_descriptors": {
          },
          "type": "rest",
          "username": "api_key_manager"
        },
        {
          "creation": 1765535267858,
          "expiration": 1765621667858,
          "id": "23gaEpsBbCMe6CnBPPEG",
          "invalidated": true,
          "invalidation": 1765535280028,
          "metadata": {
          },
          "name": "my-api-key",
          "realm": "default_native",
          "realm_type": "native",
          "role_descriptors": {
            "role-a": {
              "applications": [
              ],
              "cluster": [
                "all"
              ],
              "indices": [
                {
                  "allow_restricted_indices": false,
                  "names": [
                    "index-a"
                  ],
                  "privileges": [
                    "read"
                  ]
                }
              ],
              "metadata": {
              },
              "run_as": [
              ],
              "transient_metadata": {
                "enabled": true
              }
            },
            "role-b": {
              "applications": [
              ],
              "cluster": [
                "manage"
              ],
              "indices": [
                {
                  "allow_restricted_indices": false,
                  "names": [
                    "index-b"
                  ],
                  "privileges": [
                    "all"
                  ]
                }
              ],
              "metadata": {
              },
              "run_as": [
              ],
              "transient_metadata": {
                "enabled": true
              }
            }
          },
          "type": "rest",
          "username": "api_key_user"
        },
        {
          "creation": 1765535268289,
          "expiration": 1765621668289,
          "id": "3XgaEpsBbCMe6CnBPfG9",
          "invalidated": true,
          "invalidation": 1765535280028,
          "metadata": {
          },
          "name": "my-api-key",
          "realm": "default_native",
          "realm_type": "native",
          "role_descriptors": {
            "role-a": {
              "applications": [
              ],
              "cluster": [
                "all"
              ],
              "indices": [
                {
                  "allow_restricted_indices": false,
                  "names": [
                    "index-a"
                  ],
                  "privileges": [
                    "read"
                  ]
                }
              ],
              "metadata": {
              },
              "run_as": [
              ],
              "transient_metadata": {
                "enabled": true
              }
            },
            "role-b": {
              "applications": [
              ],
              "cluster": [
                "manage"
              ],
              "indices": [
                {
                  "allow_restricted_indices": false,
                  "names": [
                    "index-b"
                  ],
                  "privileges": [
                    "all"
                  ]
                }
              ],
              "metadata": {
              },
              "run_as": [
              ],
              "transient_metadata": {
                "enabled": true
              }
            }
          },
          "type": "rest",
          "username": "api_key_user"
        },
        {
          "creation": 1765535273316,
          "expiration": 1765621673316,
          "id": "5XgaEpsBbCMe6CnBUfFg",
          "invalidated": true,
          "invalidation": 1765535280028,
          "metadata": {
          },
          "name": "my-api-key",
          "realm": "default_native",
          "realm_type": "native",
          "role_descriptors": {
            "role-a": {
              "applications": [
                {
                  "application": "kibana-.kibana",
                  "privileges": [
                    "read"
                  ],
                  "resources": [
                    "*"
                  ]
                }
              ],
              "cluster": [
                "all"
              ],
              "indices": [
                {
                  "allow_restricted_indices": false,
                  "names": [
                    "index-a"
                  ],
                  "privileges": [
                    "read"
                  ]
                }
              ],
              "metadata": {
              },
              "run_as": [
              ],
              "transient_metadata": {
                "enabled": true
              }
            },
            "role-b": {
              "applications": [
              ],
              "cluster": [
                "manage"
              ],
              "indices": [
                {
                  "allow_restricted_indices": false,
                  "names": [
                    "index-b"
                  ],
                  "privileges": [
                    "all"
                  ]
                }
              ],
              "metadata": {
              },
              "run_as": [
              ],
              "transient_metadata": {
                "enabled": true
              }
            }
          },
          "type": "rest",
          "username": "api_key_user"
        }
      ],
      "count": 10,
      "total": 47
    },
    "statusCode": 200
  }
}