{
  "api": "cat.tasks",
  "file": "/test/platinum/ml/set_upgrade_mode.yml",
  "name": "Setting upgrade mode to disabled from enabled",
  "origin": "yaml",
  "request": {
    "args": {
      "format": "json"
    }
  },
  "response": {
    "headers": {
      "content-type": "application/json",
      "transfer-encoding": "chunked",
      "x-elastic-product": "Elasticsearch"
    },
    "payload": [
      {
        "action": "xpack/ml/trained_model_assignment[n]",
        "ip": "172.19.0.2",
        "node": "instance",
        "parent_task_id": "-",
        "running_time": "777.6ms",
        "start_time": "1745145145423",
        "task_id": "vnI7L-qSTNqSEYu4qC0SCw:158665",
        "timestamp": "10:32:25",
        "type": "trained_model_assignment"
      },
      {
        "action": "xpack/ml/trained_model_assignment[n]",
        "ip": "172.19.0.2",
        "node": "instance",
        "parent_task_id": "-",
        "running_time": "777.6ms",
        "start_time": "1745145145423",
        "task_id": "vnI7L-qSTNqSEYu4qC0SCw:158664",
        "timestamp": "10:32:25",
        "type": "trained_model_assignment"
      },
      {
        "action": "health-node[c]",
        "ip": "172.19.0.2",
        "node": "instance",
        "parent_task_id": "cluster:1460",
        "running_time": "620.9ms",
        "start_time": "1745145145580",
        "task_id": "vnI7L-qSTNqSEYu4qC0SCw:158685",
        "timestamp": "10:32:25",
        "type": "persistent"
      },
      {
        "action": "cluster:monitor/tasks/lists",
        "ip": "172.19.0.2",
        "node": "instance",
        "parent_task_id": "-",
        "running_time": "93.7micros",
        "start_time": "1745145146201",
        "task_id": "vnI7L-qSTNqSEYu4qC0SCw:158769",
        "timestamp": "10:32:26",
        "type": "transport"
      },
      {
        "action": "cluster:monitor/tasks/lists[n]",
        "ip": "172.19.0.2",
        "node": "instance",
        "parent_task_id": "vnI7L-qSTNqSEYu4qC0SCw:158769",
        "running_time": "28micros",
        "start_time": "1745145146201",
        "task_id": "vnI7L-qSTNqSEYu4qC0SCw:158770",
        "timestamp": "10:32:26",
        "type": "transport"
      }
    ],
    "statusCode": 200
  }
}