{
  "api": "esql.query",
  "file": "/test/platinum/esql/10_basic.yml",
  "name": "Test Input Params",
  "origin": "yaml",
  "request": {
    "args": {
      "body": {
        "params": [
          "foo",
          15,
          10
        ],
        "query": "row a = ? | eval b = ?, c = 1 + ?"
      }
    }
  },
  "response": {
    "headers": {
      "content-type": "application/json",
      "took-nanos": "21367994",
      "transfer-encoding": "chunked",
      "warning": "299 Elasticsearch-9.5.0-75413c350dde481cc585e352078aa5d3ba15a326 \"No limit defined, adding default limit of [1000]\"",
      "x-elastic-product": "Elasticsearch"
    },
    "payload": {
      "bytes_read": 0,
      "columns": [
        {
          "name": "a",
          "type": "keyword"
        },
        {
          "name": "b",
          "type": "integer"
        },
        {
          "name": "c",
          "type": "integer"
        }
      ],
      "completion_time_in_millis": 1781433577832,
      "cpu_nanos": 139561,
      "documents_found": 0,
      "expiration_time_in_millis": 1781865577733,
      "is_partial": false,
      "read_nanos": 0,
      "rows_emitted": 3,
      "start_time_in_millis": 1781433577811,
      "took": 21,
      "values": [
        [
          "foo",
          15,
          11
        ]
      ],
      "values_loaded": 0
    },
    "statusCode": 200
  }
}