{
  "api": "security.get_api_key",
  "file": "/test/platinum/api_key/30_update.yml",
  "name": "Test bulk update api keys",
  "origin": "yaml",
  "request": {
    "args": {
      "owner": true
    },
    "headers": {
      "Authorization": "Basic YXBpX2tleV91c2VyXzE6eC1wYWNrLXRlc3QtcGFzc3dvcmQ="
    }
  },
  "response": {
    "headers": {
      "content-length": "2877",
      "content-type": "application/json",
      "x-elastic-product": "Elasticsearch"
    },
    "payload": {
      "api_keys": [
        {
          "creation": 1767004126885,
          "id": "LiKnaZsBkwS4Y7V9PrWj",
          "invalidated": false,
          "metadata": {
            "letter": "a",
            "number": 42
          },
          "name": "user1-api-key",
          "realm": "default_native",
          "realm_type": "native",
          "role_descriptors": {
          },
          "type": "rest",
          "username": "api_key_user_1"
        },
        {
          "creation": 1767004128908,
          "id": "MCKnaZsBkwS4Y7V9RrWL",
          "invalidated": false,
          "metadata": {
          },
          "name": "user1-api-key",
          "realm": "default_native",
          "realm_type": "native",
          "role_descriptors": {
          },
          "type": "rest",
          "username": "api_key_user_1"
        },
        {
          "creation": 1767004107493,
          "expiration": 1767090507493,
          "id": "DCKmaZsBkwS4Y7V98rXk",
          "invalidated": true,
          "invalidation": 1767004108423,
          "metadata": {
          },
          "name": "user1-api-key",
          "realm": "default_native",
          "realm_type": "native",
          "role_descriptors": {
          },
          "type": "rest",
          "username": "api_key_user_1"
        },
        {
          "creation": 1767004111522,
          "expiration": 1767090511522,
          "id": "ECKnaZsBkwS4Y7V9ArWg",
          "invalidated": true,
          "invalidation": 1767004112451,
          "metadata": {
          },
          "name": "user1-api-key",
          "realm": "default_native",
          "realm_type": "native",
          "role_descriptors": {
          },
          "type": "rest",
          "username": "api_key_user_1"
        },
        {
          "creation": 1767004120585,
          "expiration": 1767090520585,
          "id": "JCKnaZsBkwS4Y7V9JrUH",
          "invalidated": false,
          "metadata": {
            "letter": "a",
            "number": 1
          },
          "name": "user1-api-key",
          "realm": "default_native",
          "realm_type": "native",
          "role_descriptors": {
          },
          "type": "rest",
          "username": "api_key_user_1"
        },
        {
          "creation": 1767004124882,
          "id": "LCKnaZsBkwS4Y7V9NrXQ",
          "invalidated": false,
          "metadata": {
            "letter": "a",
            "number": 42
          },
          "name": "user1-api-key",
          "realm": "default_native",
          "realm_type": "native",
          "role_descriptors": {
            "role-a": {
              "applications": [
              ],
              "cluster": [
                "all"
              ],
              "indices": [
                {
                  "allow_restricted_indices": false,
                  "names": [
                    "index-a"
                  ],
                  "privileges": [
                    "write"
                  ]
                },
                {
                  "allow_restricted_indices": false,
                  "names": [
                    "index-b"
                  ],
                  "privileges": [
                    "read"
                  ]
                }
              ],
              "metadata": {
              },
              "run_as": [
              ],
              "transient_metadata": {
                "enabled": true
              }
            }
          },
          "type": "rest",
          "username": "api_key_user_1"
        },
        {
          "creation": 1767004130912,
          "id": "MiKnaZsBkwS4Y7V9TrVf",
          "invalidated": false,
          "metadata": {
            "letter": "a",
            "number": 42
          },
          "name": "api-key-1",
          "realm": "default_native",
          "realm_type": "native",
          "role_descriptors": {
            "role-a": {
              "applications": [
              ],
              "cluster": [
                "all"
              ],
              "indices": [
                {
                  "allow_restricted_indices": false,
                  "names": [
                    "index-a"
                  ],
                  "privileges": [
                    "write"
                  ]
                },
                {
                  "allow_restricted_indices": false,
                  "names": [
                    "index-b"
                  ],
                  "privileges": [
                    "read"
                  ]
                }
              ],
              "metadata": {
              },
              "run_as": [
              ],
              "transient_metadata": {
                "enabled": true
              }
            }
          },
          "type": "rest",
          "username": "api_key_user_1"
        },
        {
          "creation": 1767004131586,
          "id": "NCKnaZsBkwS4Y7V9UbUA",
          "invalidated": false,
          "metadata": {
            "letter": "a",
            "number": 42
          },
          "name": "api-key-2",
          "realm": "default_native",
          "realm_type": "native",
          "role_descriptors": {
            "role-a": {
              "applications": [
              ],
              "cluster": [
                "all"
              ],
              "indices": [
                {
                  "allow_restricted_indices": false,
                  "names": [
                    "index-a"
                  ],
                  "privileges": [
                    "write"
                  ]
                },
                {
                  "allow_restricted_indices": false,
                  "names": [
                    "index-b"
                  ],
                  "privileges": [
                    "read"
                  ]
                }
              ],
              "metadata": {
              },
              "run_as": [
              ],
              "transient_metadata": {
                "enabled": true
              }
            }
          },
          "type": "rest",
          "username": "api_key_user_1"
        }
      ]
    },
    "statusCode": 200
  }
}